{"config": {"view": {"continuousWidth": 400, "continuousHeight": 300}}, "data": {"name": "data-e1354ce31ef81f8b43675f7ed1b044f7"}, "mark": {"type": "line", "clip": true}, "encoding": {"color": {"type": "nominal", "field": "Weighted by"}, "strokeDash": {"type": "nominal", "field": "Weighted by"}, "x": {"type": "temporal", "field": "Date"}, "y": {"type": "quantitative", "field": "Immunity", "scale": {"domain": [0, 1]}}}, "selection": {"selector093": {"type": "interval", "bind": "scales", "encodings": ["x", "y"]}}, "title": "Weighted average immunity: Wien", "width": 500, "$schema": "https://vega.github.io/schema/vega-lite/v4.8.1.json", "datasets": {"data-e1354ce31ef81f8b43675f7ed1b044f7": [{"Date": "2020-12-27T00:00:00", "Weighted by": "Population (Normal)", "Immunity": 0.0}, {"Date": "2020-12-28T00:00:00", "Weighted by": "Population (Normal)", "Immunity": 0.00021051838346498145}, {"Date": "2020-12-29T00:00:00", "Weighted by": "Population (Normal)", "Immunity": 0.0004964880459594474}, {"Date": "2020-12-30T00:00:00", "Weighted by": "Population (Normal)", "Immunity": 0.0008299640693243296}, {"Date": "2020-12-31T00:00:00", "Weighted by": "Population (Normal)", "Immunity": 0.0008304298179603141}, {"Date": "2021-01-01T00:00:00", "Weighted by": "Population (Normal)", "Immunity": 0.0008308955665962985}, {"Date": "2021-01-02T00:00:00", "Weighted by": "Population (Normal)", "Immunity": 0.0008313613152322831}, {"Date": "2021-01-03T00:00:00", "Weighted by": "Population (Normal)", "Immunity": 0.0008313613152322831}, {"Date": "2021-01-04T00:00:00", "Weighted by": "Population (Normal)", "Immunity": 0.0008313613152322831}, {"Date": "2021-01-05T00:00:00", "Weighted by": "Population (Normal)", "Immunity": 0.0008360188015921277}, {"Date": "2021-01-06T00:00:00", "Weighted by": "Population (Normal)", "Immunity": 0.0011224542127225782}, {"Date": "2021-01-07T00:00:00", "Weighted by": "Population (Normal)", "Immunity": 0.001570970149175625}, {"Date": "2021-01-08T00:00:00", "Weighted by": "Population (Normal)", "Immunity": 0.0022425796822652336}, {"Date": "2021-01-09T00:00:00", "Weighted by": "Population (Normal)", "Immunity": 0.0024796457379813305}, {"Date": "2021-01-10T00:00:00", "Weighted by": "Population (Normal)", "Immunity": 0.002538795814751358}, {"Date": "2021-01-11T00:00:00", "Weighted by": "Population (Normal)", "Immunity": 0.003068352013865703}, {"Date": "2021-01-12T00:00:00", "Weighted by": "Population (Normal)", "Immunity": 0.0037734954487461947}, {"Date": "2021-01-13T00:00:00", "Weighted by": "Population (Normal)", "Immunity": 0.004397132872329401}, {"Date": "2021-01-14T00:00:00", "Weighted by": "Population (Normal)", "Immunity": 0.0053919719587922355}, {"Date": "2021-01-15T00:00:00", "Weighted by": "Population (Normal)", "Immunity": 0.007511594001157568}, {"Date": "2021-01-16T00:00:00", "Weighted by": "Population (Normal)", "Immunity": 0.00881569018191409}, {"Date": "2021-01-17T00:00:00", "Weighted by": "Population (Normal)", "Immunity": 0.009953671093546399}, {"Date": "2021-01-18T00:00:00", "Weighted by": "Population (Normal)", "Immunity": 0.012285601250090272}, {"Date": "2021-01-19T00:00:00", "Weighted by": "Population (Normal)", "Immunity": 0.01414488027120177}, {"Date": "2021-01-20T00:00:00", "Weighted by": "Population (Normal)", "Immunity": 0.016122799599351513}, {"Date": "2021-01-21T00:00:00", "Weighted by": "Population (Normal)", "Immunity": 0.01819774117144678}, {"Date": "2021-01-22T00:00:00", "Weighted by": "Population (Normal)", "Immunity": 0.019757015273415383}, {"Date": "2021-01-23T00:00:00", "Weighted by": "Population (Normal)", "Immunity": 0.019930273766001608}, {"Date": "2021-01-24T00:00:00", "Weighted by": "Population (Normal)", "Immunity": 0.019931205263273577}, {"Date": "2021-01-25T00:00:00", "Weighted by": "Population (Normal)", "Immunity": 0.020091888542688216}, {"Date": "2021-01-26T00:00:00", "Weighted by": "Population (Normal)", "Immunity": 0.020571766631674464}, {"Date": "2021-01-27T00:00:00", "Weighted by": "Population (Normal)", "Immunity": 0.021528885311753294}, {"Date": "2021-01-28T00:00:00", "Weighted by": "Population (Normal)", "Immunity": 0.022311761670666525}, {"Date": "2021-01-29T00:00:00", "Weighted by": "Population (Normal)", "Immunity": 0.022849492019998932}, {"Date": "2021-01-30T00:00:00", "Weighted by": "Population (Normal)", "Immunity": 0.02286230795718462}, {"Date": "2021-01-31T00:00:00", "Weighted by": "Population (Normal)", "Immunity": 0.02287093738977718}, {"Date": "2021-02-01T00:00:00", "Weighted by": "Population (Normal)", "Immunity": 0.023110771771655488}, {"Date": "2021-02-02T00:00:00", "Weighted by": "Population (Normal)", "Immunity": 0.02347758283784307}, {"Date": "2021-02-03T00:00:00", "Weighted by": "Population (Normal)", "Immunity": 0.023822922368598707}, {"Date": "2021-02-04T00:00:00", "Weighted by": "Population (Normal)", "Immunity": 0.02418851934845429}, {"Date": "2021-02-05T00:00:00", "Weighted by": "Population (Normal)", "Immunity": 0.024631310239876244}, {"Date": "2021-02-06T00:00:00", "Weighted by": "Population (Normal)", "Immunity": 0.024828201550890633}, {"Date": "2021-02-07T00:00:00", "Weighted by": "Population (Normal)", "Immunity": 0.024929070145931084}, {"Date": "2021-02-08T00:00:00", "Weighted by": "Population (Normal)", "Immunity": 0.025355617399531738}, {"Date": "2021-02-09T00:00:00", "Weighted by": "Population (Normal)", "Immunity": 0.025574289000691815}, {"Date": "2021-02-10T00:00:00", "Weighted by": "Population (Normal)", "Immunity": 0.02592890163912121}, {"Date": "2021-02-11T00:00:00", "Weighted by": "Population (Normal)", "Immunity": 0.026493802403262965}, {"Date": "2021-02-12T00:00:00", "Weighted by": "Population (Normal)", "Immunity": 0.027609657638120632}, {"Date": "2021-02-13T00:00:00", "Weighted by": "Population (Normal)", "Immunity": 0.02778821205901716}, {"Date": "2021-02-14T00:00:00", "Weighted by": "Population (Normal)", "Immunity": 0.027807401949445865}, {"Date": "2021-02-15T00:00:00", "Weighted by": "Population (Normal)", "Immunity": 0.028459936720983074}, {"Date": "2021-02-16T00:00:00", "Weighted by": "Population (Normal)", "Immunity": 0.028865530519095173}, {"Date": "2021-02-17T00:00:00", "Weighted by": "Population (Normal)", "Immunity": 0.029843660219100718}, {"Date": "2021-02-18T00:00:00", "Weighted by": "Population (Normal)", "Immunity": 0.03082351685225093}, {"Date": "2021-02-19T00:00:00", "Weighted by": "Population (Normal)", "Immunity": 0.031550137055694115}, {"Date": "2021-02-20T00:00:00", "Weighted by": "Population (Normal)", "Immunity": 0.03178528255242812}, {"Date": "2021-02-21T00:00:00", "Weighted by": "Population (Normal)", "Immunity": 0.031798543305726824}, {"Date": "2021-02-22T00:00:00", "Weighted by": "Population (Normal)", "Immunity": 0.0321241434673259}, {"Date": "2021-02-23T00:00:00", "Weighted by": "Population (Normal)", "Immunity": 0.032599924014941634}, {"Date": "2021-02-24T00:00:00", "Weighted by": "Population (Normal)", "Immunity": 0.03419204124544325}, {"Date": "2021-02-25T00:00:00", "Weighted by": "Population (Normal)", "Immunity": 0.03506046882571686}, {"Date": "2021-02-26T00:00:00", "Weighted by": "Population (Normal)", "Immunity": 0.036826681849723326}, {"Date": "2021-02-27T00:00:00", "Weighted by": "Population (Normal)", "Immunity": 0.03796979646261294}, {"Date": "2021-02-28T00:00:00", "Weighted by": "Population (Normal)", "Immunity": 0.03908394046371818}, {"Date": "2021-03-01T00:00:00", "Weighted by": "Population (Normal)", "Immunity": 0.04033245032973956}, {"Date": "2021-03-02T00:00:00", "Weighted by": "Population (Normal)", "Immunity": 0.04144162808977122}, {"Date": "2021-03-03T00:00:00", "Weighted by": "Population (Normal)", "Immunity": 0.04304612690760698}, {"Date": "2021-03-04T00:00:00", "Weighted by": "Population (Normal)", "Immunity": 0.044938479315004116}, {"Date": "2021-03-05T00:00:00", "Weighted by": "Population (Normal)", "Immunity": 0.04716001134542744}, {"Date": "2021-03-06T00:00:00", "Weighted by": "Population (Normal)", "Immunity": 0.04978800587366594}, {"Date": "2021-03-07T00:00:00", "Weighted by": "Population (Normal)", "Immunity": 0.051621045977240064}, {"Date": "2021-03-08T00:00:00", "Weighted by": "Population (Normal)", "Immunity": 0.05437422222594357}, {"Date": "2021-03-09T00:00:00", "Weighted by": "Population (Normal)", "Immunity": 0.057629967418527994}, {"Date": "2021-03-10T00:00:00", "Weighted by": "Population (Normal)", "Immunity": 0.06085705075404182}, {"Date": "2021-03-11T00:00:00", "Weighted by": "Population (Normal)", "Immunity": 0.06371661131758719}, {"Date": "2021-03-12T00:00:00", "Weighted by": "Population (Normal)", "Immunity": 0.0669088943336707}, {"Date": "2021-03-13T00:00:00", "Weighted by": "Population (Normal)", "Immunity": 0.06932410453283319}, {"Date": "2021-03-14T00:00:00", "Weighted by": "Population (Normal)", "Immunity": 0.07098410070218147}, {"Date": "2021-03-15T00:00:00", "Weighted by": "Population (Normal)", "Immunity": 0.07388679796242821}, {"Date": "2021-03-16T00:00:00", "Weighted by": "Population (Normal)", "Immunity": 0.07664826872335684}, {"Date": "2021-03-17T00:00:00", "Weighted by": "Population (Normal)", "Immunity": 0.07943123195224035}, {"Date": "2021-03-18T00:00:00", "Weighted by": "Population (Normal)", "Immunity": 0.0821703572449032}, {"Date": "2021-03-19T00:00:00", "Weighted by": "Population (Normal)", "Immunity": 0.08460068595877758}, {"Date": "2021-03-20T00:00:00", "Weighted by": "Population (Normal)", "Immunity": 0.08708284359951479}, {"Date": "2021-03-21T00:00:00", "Weighted by": "Population (Normal)", "Immunity": 0.08900999109321149}, {"Date": "2021-03-22T00:00:00", "Weighted by": "Population (Normal)", "Immunity": 0.09136261304870683}, {"Date": "2021-03-23T00:00:00", "Weighted by": "Population (Normal)", "Immunity": 0.09336451058191368}, {"Date": "2021-03-24T00:00:00", "Weighted by": "Population (Normal)", "Immunity": 0.09540424365038082}, {"Date": "2021-03-25T00:00:00", "Weighted by": "Population (Normal)", "Immunity": 0.09816626912316802}, {"Date": "2021-03-26T00:00:00", "Weighted by": "Population (Normal)", "Immunity": 0.10072757786636885}, {"Date": "2021-03-27T00:00:00", "Weighted by": "Population (Normal)", "Immunity": 0.10240607838601876}, {"Date": "2021-03-28T00:00:00", "Weighted by": "Population (Normal)", "Immunity": 0.10337529083124095}, {"Date": "2021-03-29T00:00:00", "Weighted by": "Population (Normal)", "Immunity": 0.10547086140471881}, {"Date": "2021-03-30T00:00:00", "Weighted by": "Population (Normal)", "Immunity": 0.10773325371997099}, {"Date": "2021-03-31T00:00:00", "Weighted by": "Population (Normal)", "Immunity": 0.11021329194275792}, {"Date": "2021-04-01T00:00:00", "Weighted by": "Population (Normal)", "Immunity": 0.11309146675235048}, {"Date": "2021-04-02T00:00:00", "Weighted by": "Population (Normal)", "Immunity": 0.11646164481485706}, {"Date": "2021-04-03T00:00:00", "Weighted by": "Population (Normal)", "Immunity": 0.11920551655710236}, {"Date": "2021-04-04T00:00:00", "Weighted by": "Population (Normal)", "Immunity": 0.1212533400456957}, {"Date": "2021-04-05T00:00:00", "Weighted by": "Population (Normal)", "Immunity": 0.12302119103962421}, {"Date": "2021-04-06T00:00:00", "Weighted by": "Population (Normal)", "Immunity": 0.1261353120149542}, {"Date": "2021-04-07T00:00:00", "Weighted by": "Population (Normal)", "Immunity": 0.12931526054188022}, {"Date": "2021-04-08T00:00:00", "Weighted by": "Population (Normal)", "Immunity": 0.1323862866855548}, {"Date": "2021-04-09T00:00:00", "Weighted by": "Population (Normal)", "Immunity": 0.13574819640148997}, {"Date": "2021-04-10T00:00:00", "Weighted by": "Population (Normal)", "Immunity": 0.13830413071941938}, {"Date": "2021-04-11T00:00:00", "Weighted by": "Population (Normal)", "Immunity": 0.13953069283511138}, {"Date": "2021-04-12T00:00:00", "Weighted by": "Population (Normal)", "Immunity": 0.14280602563606087}, {"Date": "2021-04-13T00:00:00", "Weighted by": "Population (Normal)", "Immunity": 0.14630748724947695}, {"Date": "2021-04-14T00:00:00", "Weighted by": "Population (Normal)", "Immunity": 0.1496553460093715}, {"Date": "2021-04-15T00:00:00", "Weighted by": "Population (Normal)", "Immunity": 0.15318297327649458}, {"Date": "2021-04-16T00:00:00", "Weighted by": "Population (Normal)", "Immunity": 0.1565128352997694}, {"Date": "2021-04-17T00:00:00", "Weighted by": "Population (Normal)", "Immunity": 0.1588812351444501}, {"Date": "2021-04-18T00:00:00", "Weighted by": "Population (Normal)", "Immunity": 0.16023556414719334}, {"Date": "2021-04-19T00:00:00", "Weighted by": "Population (Normal)", "Immunity": 0.165172635750028}, {"Date": "2021-04-20T00:00:00", "Weighted by": "Population (Normal)", "Immunity": 0.17040807430208352}, {"Date": "2021-04-21T00:00:00", "Weighted by": "Population (Normal)", "Immunity": 0.17570161107163007}, {"Date": "2021-04-22T00:00:00", "Weighted by": "Population (Normal)", "Immunity": 0.18078553478932988}, {"Date": "2021-04-23T00:00:00", "Weighted by": "Population (Normal)", "Immunity": 0.18604715992761534}, {"Date": "2021-04-24T00:00:00", "Weighted by": "Population (Normal)", "Immunity": 0.1902092048676489}, {"Date": "2021-04-25T00:00:00", "Weighted by": "Population (Normal)", "Immunity": 0.19339366958640472}, {"Date": "2021-04-26T00:00:00", "Weighted by": "Population (Normal)", "Immunity": 0.19719738636518253}, {"Date": "2021-04-27T00:00:00", "Weighted by": "Population (Normal)", "Immunity": 0.20174888612812167}, {"Date": "2021-04-28T00:00:00", "Weighted by": "Population (Normal)", "Immunity": 0.20650869589335297}, {"Date": "2021-04-29T00:00:00", "Weighted by": "Population (Normal)", "Immunity": 0.211777150267256}, {"Date": "2021-04-30T00:00:00", "Weighted by": "Population (Normal)", "Immunity": 0.2169547941234035}, {"Date": "2021-05-01T00:00:00", "Weighted by": "Population (Normal)", "Immunity": 0.21996033810211096}, {"Date": "2021-05-02T00:00:00", "Weighted by": "Population (Normal)", "Immunity": 0.2228497693759282}, {"Date": "2021-05-03T00:00:00", "Weighted by": "Population (Normal)", "Immunity": 0.2260771248342406}, {"Date": "2021-05-04T00:00:00", "Weighted by": "Population (Normal)", "Immunity": 0.22989939306149662}, {"Date": "2021-05-05T00:00:00", "Weighted by": "Population (Normal)", "Immunity": 0.2348391440272709}, {"Date": "2021-05-06T00:00:00", "Weighted by": "Population (Normal)", "Immunity": 0.24004240405839758}, {"Date": "2021-05-07T00:00:00", "Weighted by": "Population (Normal)", "Immunity": 0.24508788519767105}, {"Date": "2021-05-08T00:00:00", "Weighted by": "Population (Normal)", "Immunity": 0.24776925242634107}, {"Date": "2021-05-09T00:00:00", "Weighted by": "Population (Normal)", "Immunity": 0.24997193995296463}, {"Date": "2021-05-10T00:00:00", "Weighted by": "Population (Normal)", "Immunity": 0.2543912456002453}, {"Date": "2021-05-11T00:00:00", "Weighted by": "Population (Normal)", "Immunity": 0.258752918778671}, {"Date": "2021-05-12T00:00:00", "Weighted by": "Population (Normal)", "Immunity": 0.2638787337079557}, {"Date": "2021-05-13T00:00:00", "Weighted by": "Population (Normal)", "Immunity": 0.26533573150271444}, {"Date": "2021-05-14T00:00:00", "Weighted by": "Population (Normal)", "Immunity": 0.2696173482470582}, {"Date": "2021-05-15T00:00:00", "Weighted by": "Population (Normal)", "Immunity": 0.27354072056023804}, {"Date": "2021-05-16T00:00:00", "Weighted by": "Population (Normal)", "Immunity": 0.2762933734958674}, {"Date": "2021-05-17T00:00:00", "Weighted by": "Population (Normal)", "Immunity": 0.2806809349720708}, {"Date": "2021-05-18T00:00:00", "Weighted by": "Population (Normal)", "Immunity": 0.28535781008131234}, {"Date": "2021-05-19T00:00:00", "Weighted by": "Population (Normal)", "Immunity": 0.2911749215815359}, {"Date": "2021-05-20T00:00:00", "Weighted by": "Population (Normal)", "Immunity": 0.29767056604681974}, {"Date": "2021-05-21T00:00:00", "Weighted by": "Population (Normal)", "Immunity": 0.30404907734671904}, {"Date": "2021-05-22T00:00:00", "Weighted by": "Population (Normal)", "Immunity": 0.30883045284373556}, {"Date": "2021-05-23T00:00:00", "Weighted by": "Population (Normal)", "Immunity": 0.3118853661778574}, {"Date": "2021-05-24T00:00:00", "Weighted by": "Population (Normal)", "Immunity": 0.31382998709509957}, {"Date": "2021-05-25T00:00:00", "Weighted by": "Population (Normal)", "Immunity": 0.3173264301361347}, {"Date": "2021-05-26T00:00:00", "Weighted by": "Population (Normal)", "Immunity": 0.32143065944773724}, {"Date": "2021-05-27T00:00:00", "Weighted by": "Population (Normal)", "Immunity": 0.3256390489936167}, {"Date": "2021-05-28T00:00:00", "Weighted by": "Population (Normal)", "Immunity": 0.32984479057534083}, {"Date": "2021-05-29T00:00:00", "Weighted by": "Population (Normal)", "Immunity": 0.3323841044700356}, {"Date": "2021-05-30T00:00:00", "Weighted by": "Population (Normal)", "Immunity": 0.33362594732749246}, {"Date": "2021-05-31T00:00:00", "Weighted by": "Population (Normal)", "Immunity": 0.3376186219910807}, {"Date": "2021-06-01T00:00:00", "Weighted by": "Population (Normal)", "Immunity": 0.34240159882610405}, {"Date": "2021-06-02T00:00:00", "Weighted by": "Population (Normal)", "Immunity": 0.3485608628804616}, {"Date": "2021-06-03T00:00:00", "Weighted by": "Population (Normal)", "Immunity": 0.35176784576079784}, {"Date": "2021-06-04T00:00:00", "Weighted by": "Population (Normal)", "Immunity": 0.35645211005064625}, {"Date": "2021-06-05T00:00:00", "Weighted by": "Population (Normal)", "Immunity": 0.3598208542353297}, {"Date": "2021-06-06T00:00:00", "Weighted by": "Population (Normal)", "Immunity": 0.3622227408836246}, {"Date": "2021-06-07T00:00:00", "Weighted by": "Population (Normal)", "Immunity": 0.3663202037571785}, {"Date": "2021-06-08T00:00:00", "Weighted by": "Population (Normal)", "Immunity": 0.3708953991361148}, {"Date": "2020-12-27T00:00:00", "Weighted by": "Population (FDF)", "Immunity": 0.0}, {"Date": "2020-12-28T00:00:00", "Weighted by": "Population (FDF)", "Immunity": 0.00029249014339824853}, {"Date": "2020-12-29T00:00:00", "Weighted by": "Population (FDF)", "Immunity": 0.0006781300139933916}, {"Date": "2020-12-30T00:00:00", "Weighted by": "Population (FDF)", "Immunity": 0.001130371939534314}, {"Date": "2020-12-31T00:00:00", "Weighted by": "Population (FDF)", "Immunity": 0.0011308376881702987}, {"Date": "2021-01-01T00:00:00", "Weighted by": "Population (FDF)", "Immunity": 0.0011313034368062832}, {"Date": "2021-01-02T00:00:00", "Weighted by": "Population (FDF)", "Immunity": 0.0011317691854422676}, {"Date": "2021-01-03T00:00:00", "Weighted by": "Population (FDF)", "Immunity": 0.0011317691854422676}, {"Date": "2021-01-04T00:00:00", "Weighted by": "Population (FDF)", "Immunity": 0.0011317691854422676}, {"Date": "2021-01-05T00:00:00", "Weighted by": "Population (FDF)", "Immunity": 0.0011382896663460502}, {"Date": "2021-01-06T00:00:00", "Weighted by": "Population (FDF)", "Immunity": 0.0016021753077865848}, {"Date": "2021-01-07T00:00:00", "Weighted by": "Population (FDF)", "Immunity": 0.0022570178899807528}, {"Date": "2021-01-08T00:00:00", "Weighted by": "Population (FDF)", "Immunity": 0.0031987616319413556}, {"Date": "2021-01-09T00:00:00", "Weighted by": "Population (FDF)", "Immunity": 0.003532237655306238}, {"Date": "2021-01-10T00:00:00", "Weighted by": "Population (FDF)", "Immunity": 0.0036309763661349454}, {"Date": "2021-01-11T00:00:00", "Weighted by": "Population (FDF)", "Immunity": 0.004361270227358598}, {"Date": "2021-01-12T00:00:00", "Weighted by": "Population (FDF)", "Immunity": 0.005386848723796407}, {"Date": "2021-01-13T00:00:00", "Weighted by": "Population (FDF)", "Immunity": 0.006241963219463896}, {"Date": "2021-01-14T00:00:00", "Weighted by": "Population (FDF)", "Immunity": 0.007703482439183171}, {"Date": "2021-01-15T00:00:00", "Weighted by": "Population (FDF)", "Immunity": 0.011029393448748285}, {"Date": "2021-01-16T00:00:00", "Weighted by": "Population (FDF)", "Immunity": 0.013159261961105277}, {"Date": "2021-01-17T00:00:00", "Weighted by": "Population (FDF)", "Immunity": 0.015040886450482545}, {"Date": "2021-01-18T00:00:00", "Weighted by": "Population (FDF)", "Immunity": 0.018816710642408665}, {"Date": "2021-01-19T00:00:00", "Weighted by": "Population (FDF)", "Immunity": 0.02189204888581413}, {"Date": "2021-01-20T00:00:00", "Weighted by": "Population (FDF)", "Immunity": 0.025210507917203497}, {"Date": "2021-01-21T00:00:00", "Weighted by": "Population (FDF)", "Immunity": 0.028328229286483556}, {"Date": "2021-01-22T00:00:00", "Weighted by": "Population (FDF)", "Immunity": 0.030957380336615905}, {"Date": "2021-01-23T00:00:00", "Weighted by": "Population (FDF)", "Immunity": 0.031249870480014152}, {"Date": "2021-01-24T00:00:00", "Weighted by": "Population (FDF)", "Immunity": 0.031251267725922106}, {"Date": "2021-01-25T00:00:00", "Weighted by": "Population (FDF)", "Immunity": 0.031490662524818115}, {"Date": "2021-01-26T00:00:00", "Weighted by": "Population (FDF)", "Immunity": 0.032271257238728104}, {"Date": "2021-01-27T00:00:00", "Weighted by": "Population (FDF)", "Immunity": 0.03360981881854747}, {"Date": "2021-01-28T00:00:00", "Weighted by": "Population (FDF)", "Immunity": 0.035285116662183626}, {"Date": "2021-01-29T00:00:00", "Weighted by": "Population (FDF)", "Immunity": 0.0367522248655347}, {"Date": "2021-01-30T00:00:00", "Weighted by": "Population (FDF)", "Immunity": 0.036836991117283883}, {"Date": "2021-01-31T00:00:00", "Weighted by": "Population (FDF)", "Immunity": 0.036884497478154296}, {"Date": "2021-02-01T00:00:00", "Weighted by": "Population (FDF)", "Immunity": 0.03748624471584624}, {"Date": "2021-02-02T00:00:00", "Weighted by": "Population (FDF)", "Immunity": 0.03873538255755659}, {"Date": "2021-02-03T00:00:00", "Weighted by": "Population (FDF)", "Immunity": 0.039607729752755505}, {"Date": "2021-02-04T00:00:00", "Weighted by": "Population (FDF)", "Immunity": 0.04097190750755403}, {"Date": "2021-02-05T00:00:00", "Weighted by": "Population (FDF)", "Immunity": 0.04343851228372779}, {"Date": "2021-02-06T00:00:00", "Weighted by": "Population (FDF)", "Immunity": 0.04490655198435085}, {"Date": "2021-02-07T00:00:00", "Weighted by": "Population (FDF)", "Immunity": 0.046124018918814264}, {"Date": "2021-02-08T00:00:00", "Weighted by": "Population (FDF)", "Immunity": 0.04842388568330558}, {"Date": "2021-02-09T00:00:00", "Weighted by": "Population (FDF)", "Immunity": 0.049640421120497026}, {"Date": "2021-02-10T00:00:00", "Weighted by": "Population (FDF)", "Immunity": 0.051379992275899025}, {"Date": "2021-02-11T00:00:00", "Weighted by": "Population (FDF)", "Immunity": 0.05414141593865096}, {"Date": "2021-02-12T00:00:00", "Weighted by": "Population (FDF)", "Immunity": 0.057468724194124035}, {"Date": "2021-02-13T00:00:00", "Weighted by": "Population (FDF)", "Immunity": 0.05787951449106234}, {"Date": "2021-02-14T00:00:00", "Weighted by": "Population (FDF)", "Immunity": 0.0579107196496733}, {"Date": "2021-02-15T00:00:00", "Weighted by": "Population (FDF)", "Immunity": 0.05935221167804524}, {"Date": "2021-02-16T00:00:00", "Weighted by": "Population (FDF)", "Immunity": 0.06076855328007402}, {"Date": "2021-02-17T00:00:00", "Weighted by": "Population (FDF)", "Immunity": 0.06353975766418163}, {"Date": "2021-02-18T00:00:00", "Weighted by": "Population (FDF)", "Immunity": 0.06595093835267325}, {"Date": "2021-02-19T00:00:00", "Weighted by": "Population (FDF)", "Immunity": 0.06786376800066148}, {"Date": "2021-02-20T00:00:00", "Weighted by": "Population (FDF)", "Immunity": 0.06815113490906388}, {"Date": "2021-02-21T00:00:00", "Weighted by": "Population (FDF)", "Immunity": 0.06817209359768318}, {"Date": "2021-02-22T00:00:00", "Weighted by": "Population (FDF)", "Immunity": 0.06885627834394438}, {"Date": "2021-02-23T00:00:00", "Weighted by": "Population (FDF)", "Immunity": 0.06967320145146115}, {"Date": "2021-02-24T00:00:00", "Weighted by": "Population (FDF)", "Immunity": 0.07216515551294625}, {"Date": "2021-02-25T00:00:00", "Weighted by": "Population (FDF)", "Immunity": 0.07306473068739266}, {"Date": "2021-02-26T00:00:00", "Weighted by": "Population (FDF)", "Immunity": 0.07490394588524163}, {"Date": "2021-02-27T00:00:00", "Weighted by": "Population (FDF)", "Immunity": 0.07608838129846533}, {"Date": "2021-02-28T00:00:00", "Weighted by": "Population (FDF)", "Immunity": 0.077251852789939}, {"Date": "2021-03-01T00:00:00", "Weighted by": "Population (FDF)", "Immunity": 0.07853455593222468}, {"Date": "2021-03-02T00:00:00", "Weighted by": "Population (FDF)", "Immunity": 0.07966944929671957}, {"Date": "2021-03-03T00:00:00", "Weighted by": "Population (FDF)", "Immunity": 0.08132126608271906}, {"Date": "2021-03-04T00:00:00", "Weighted by": "Population (FDF)", "Immunity": 0.08327057588510557}, {"Date": "2021-03-05T00:00:00", "Weighted by": "Population (FDF)", "Immunity": 0.0855519225999031}, {"Date": "2021-03-06T00:00:00", "Weighted by": "Population (FDF)", "Immunity": 0.08826648357686578}, {"Date": "2021-03-07T00:00:00", "Weighted by": "Population (FDF)", "Immunity": 0.09018367242276161}, {"Date": "2021-03-08T00:00:00", "Weighted by": "Population (FDF)", "Immunity": 0.09407241710982561}, {"Date": "2021-03-09T00:00:00", "Weighted by": "Population (FDF)", "Immunity": 0.09976386544155585}, {"Date": "2021-03-10T00:00:00", "Weighted by": "Population (FDF)", "Immunity": 0.10559224387226555}, {"Date": "2021-03-11T00:00:00", "Weighted by": "Population (FDF)", "Immunity": 0.11097443510970213}, {"Date": "2021-03-12T00:00:00", "Weighted by": "Population (FDF)", "Immunity": 0.11719450814327474}, {"Date": "2021-03-13T00:00:00", "Weighted by": "Population (FDF)", "Immunity": 0.12149476529931938}, {"Date": "2021-03-14T00:00:00", "Weighted by": "Population (FDF)", "Immunity": 0.12441547499557801}, {"Date": "2021-03-15T00:00:00", "Weighted by": "Population (FDF)", "Immunity": 0.1293528762856494}, {"Date": "2021-03-16T00:00:00", "Weighted by": "Population (FDF)", "Immunity": 0.13392885663419682}, {"Date": "2021-03-17T00:00:00", "Weighted by": "Population (FDF)", "Immunity": 0.13839724904783185}, {"Date": "2021-03-18T00:00:00", "Weighted by": "Population (FDF)", "Immunity": 0.14271427315477192}, {"Date": "2021-03-19T00:00:00", "Weighted by": "Population (FDF)", "Immunity": 0.14690601087863217}, {"Date": "2021-03-20T00:00:00", "Weighted by": "Population (FDF)", "Immunity": 0.15116574790334616}, {"Date": "2021-03-21T00:00:00", "Weighted by": "Population (FDF)", "Immunity": 0.15407574538097715}, {"Date": "2021-03-22T00:00:00", "Weighted by": "Population (FDF)", "Immunity": 0.1583000855093563}, {"Date": "2021-03-23T00:00:00", "Weighted by": "Population (FDF)", "Immunity": 0.16212714205124076}, {"Date": "2021-03-24T00:00:00", "Weighted by": "Population (FDF)", "Immunity": 0.16596211631993685}, {"Date": "2021-03-25T00:00:00", "Weighted by": "Population (FDF)", "Immunity": 0.1709344487577071}, {"Date": "2021-03-26T00:00:00", "Weighted by": "Population (FDF)", "Immunity": 0.1757502896537865}, {"Date": "2021-03-27T00:00:00", "Weighted by": "Population (FDF)", "Immunity": 0.17975153618552914}, {"Date": "2021-03-28T00:00:00", "Weighted by": "Population (FDF)", "Immunity": 0.1827146290076624}, {"Date": "2021-03-29T00:00:00", "Weighted by": "Population (FDF)", "Immunity": 0.18867714304553557}, {"Date": "2021-03-30T00:00:00", "Weighted by": "Population (FDF)", "Immunity": 0.19435415316955032}, {"Date": "2021-03-31T00:00:00", "Weighted by": "Population (FDF)", "Immunity": 0.20017507962208425}, {"Date": "2021-04-01T00:00:00", "Weighted by": "Population (FDF)", "Immunity": 0.20710635082280515}, {"Date": "2021-04-02T00:00:00", "Weighted by": "Population (FDF)", "Immunity": 0.2159420681960666}, {"Date": "2021-04-03T00:00:00", "Weighted by": "Population (FDF)", "Immunity": 0.22282909327636896}, {"Date": "2021-04-04T00:00:00", "Weighted by": "Population (FDF)", "Immunity": 0.22691091432213692}, {"Date": "2021-04-05T00:00:00", "Weighted by": "Population (FDF)", "Immunity": 0.2307379708640213}, {"Date": "2021-04-06T00:00:00", "Weighted by": "Population (FDF)", "Immunity": 0.23969897462036255}, {"Date": "2021-04-07T00:00:00", "Weighted by": "Population (FDF)", "Immunity": 0.24629600576063032}, {"Date": "2021-04-08T00:00:00", "Weighted by": "Population (FDF)", "Immunity": 0.2487545096504164}, {"Date": "2021-04-09T00:00:00", "Weighted by": "Population (FDF)", "Immunity": 0.25148556545547607}, {"Date": "2021-04-10T00:00:00", "Weighted by": "Population (FDF)", "Immunity": 0.2536718471172253}, {"Date": "2021-04-11T00:00:00", "Weighted by": "Population (FDF)", "Immunity": 0.25463766326059634}, {"Date": "2021-04-12T00:00:00", "Weighted by": "Population (FDF)", "Immunity": 0.2577283450433355}, {"Date": "2021-04-13T00:00:00", "Weighted by": "Population (FDF)", "Immunity": 0.26103411373267704}, {"Date": "2021-04-14T00:00:00", "Weighted by": "Population (FDF)", "Immunity": 0.26412798249203784}, {"Date": "2021-04-15T00:00:00", "Weighted by": "Population (FDF)", "Immunity": 0.2674130436830356}, {"Date": "2021-04-16T00:00:00", "Weighted by": "Population (FDF)", "Immunity": 0.2705678470167492}, {"Date": "2021-04-17T00:00:00", "Weighted by": "Population (FDF)", "Immunity": 0.2728505334130165}, {"Date": "2021-04-18T00:00:00", "Weighted by": "Population (FDF)", "Immunity": 0.2741365281945385}, {"Date": "2021-04-19T00:00:00", "Weighted by": "Population (FDF)", "Immunity": 0.28909668313707354}, {"Date": "2021-04-20T00:00:00", "Weighted by": "Population (FDF)", "Immunity": 0.30988677075014837}, {"Date": "2021-04-21T00:00:00", "Weighted by": "Population (FDF)", "Immunity": 0.33133123519678137}, {"Date": "2021-04-22T00:00:00", "Weighted by": "Population (FDF)", "Immunity": 0.34555212145887126}, {"Date": "2021-04-23T00:00:00", "Weighted by": "Population (FDF)", "Immunity": 0.35082211437321226}, {"Date": "2021-04-24T00:00:00", "Weighted by": "Population (FDF)", "Immunity": 0.3550557904068341}, {"Date": "2021-04-25T00:00:00", "Weighted by": "Population (FDF)", "Immunity": 0.35821560707979794}, {"Date": "2021-04-26T00:00:00", "Weighted by": "Population (FDF)", "Immunity": 0.36083537512651087}, {"Date": "2021-04-27T00:00:00", "Weighted by": "Population (FDF)", "Immunity": 0.3642480985419451}, {"Date": "2021-04-28T00:00:00", "Weighted by": "Population (FDF)", "Immunity": 0.36780320497859126}, {"Date": "2021-04-29T00:00:00", "Weighted by": "Population (FDF)", "Immunity": 0.3718356409695526}, {"Date": "2021-04-30T00:00:00", "Weighted by": "Population (FDF)", "Immunity": 0.388493167101191}, {"Date": "2021-05-01T00:00:00", "Weighted by": "Population (FDF)", "Immunity": 0.4002887170561337}, {"Date": "2021-05-02T00:00:00", "Weighted by": "Population (FDF)", "Immunity": 0.41146016383885725}, {"Date": "2021-05-03T00:00:00", "Weighted by": "Population (FDF)", "Immunity": 0.42969655168082926}, {"Date": "2021-05-04T00:00:00", "Weighted by": "Population (FDF)", "Immunity": 0.43829919587713023}, {"Date": "2021-05-05T00:00:00", "Weighted by": "Population (FDF)", "Immunity": 0.4430626217357039}, {"Date": "2021-05-06T00:00:00", "Weighted by": "Population (FDF)", "Immunity": 0.44818901754250084}, {"Date": "2021-05-07T00:00:00", "Weighted by": "Population (FDF)", "Immunity": 0.4532425367705931}, {"Date": "2021-05-08T00:00:00", "Weighted by": "Population (FDF)", "Immunity": 0.4559239353980476}, {"Date": "2021-05-09T00:00:00", "Weighted by": "Population (FDF)", "Immunity": 0.4582055437693822}, {"Date": "2021-05-10T00:00:00", "Weighted by": "Population (FDF)", "Immunity": 0.4624649144749443}, {"Date": "2021-05-11T00:00:00", "Weighted by": "Population (FDF)", "Immunity": 0.4856186764156403}, {"Date": "2021-05-12T00:00:00", "Weighted by": "Population (FDF)", "Immunity": 0.5148285678700425}, {"Date": "2021-05-13T00:00:00", "Weighted by": "Population (FDF)", "Immunity": 0.5239823915616814}, {"Date": "2021-05-14T00:00:00", "Weighted by": "Population (FDF)", "Immunity": 0.5345348479409201}, {"Date": "2021-05-15T00:00:00", "Weighted by": "Population (FDF)", "Immunity": 0.5389265959217165}, {"Date": "2021-05-16T00:00:00", "Weighted by": "Population (FDF)", "Immunity": 0.5419093914810911}, {"Date": "2021-05-17T00:00:00", "Weighted by": "Population (FDF)", "Immunity": 0.5468749365482897}, {"Date": "2021-05-18T00:00:00", "Weighted by": "Population (FDF)", "Immunity": 0.5611942946315405}, {"Date": "2021-05-19T00:00:00", "Weighted by": "Population (FDF)", "Immunity": 0.5963359607138408}, {"Date": "2021-05-20T00:00:00", "Weighted by": "Population (FDF)", "Immunity": 0.6332321019078948}, {"Date": "2021-05-21T00:00:00", "Weighted by": "Population (FDF)", "Immunity": 0.6733051145479987}, {"Date": "2021-05-22T00:00:00", "Weighted by": "Population (FDF)", "Immunity": 0.6915252535190187}, {"Date": "2021-05-23T00:00:00", "Weighted by": "Population (FDF)", "Immunity": 0.6943469680810423}, {"Date": "2021-05-24T00:00:00", "Weighted by": "Population (FDF)", "Immunity": 0.6970711161535232}, {"Date": "2021-05-25T00:00:00", "Weighted by": "Population (FDF)", "Immunity": 0.7014249291695753}, {"Date": "2021-05-26T00:00:00", "Weighted by": "Population (FDF)", "Immunity": 0.7065450609188749}, {"Date": "2021-05-27T00:00:00", "Weighted by": "Population (FDF)", "Immunity": 0.7118184606013286}, {"Date": "2021-05-28T00:00:00", "Weighted by": "Population (FDF)", "Immunity": 0.7172091870750044}, {"Date": "2021-05-29T00:00:00", "Weighted by": "Population (FDF)", "Immunity": 0.7207252491231888}, {"Date": "2021-05-30T00:00:00", "Weighted by": "Population (FDF)", "Immunity": 0.7228650187189086}, {"Date": "2021-05-31T00:00:00", "Weighted by": "Population (FDF)", "Immunity": 0.7278864693218177}, {"Date": "2021-06-01T00:00:00", "Weighted by": "Population (FDF)", "Immunity": 0.7340779380627577}, {"Date": "2021-06-02T00:00:00", "Weighted by": "Population (FDF)", "Immunity": 0.7417977845017693}, {"Date": "2021-06-03T00:00:00", "Weighted by": "Population (FDF)", "Immunity": 0.744508441563199}, {"Date": "2021-06-04T00:00:00", "Weighted by": "Population (FDF)", "Immunity": 0.7483871962036776}, {"Date": "2021-06-05T00:00:00", "Weighted by": "Population (FDF)", "Immunity": 0.7512049754513836}, {"Date": "2021-06-06T00:00:00", "Weighted by": "Population (FDF)", "Immunity": 0.7532225985424684}, {"Date": "2021-06-07T00:00:00", "Weighted by": "Population (FDF)", "Immunity": 0.7566057966342596}, {"Date": "2021-06-08T00:00:00", "Weighted by": "Population (FDF)", "Immunity": 0.7604519488702193}]}}